[
    {
        "外文": "O sistema informático",
        "中文": "电脑系统",
        "语种": "pt",
        "类别": "计算机"
    },
    {
        "外文": "Uma interface local",
        "中文": "本地接口",
        "语种": "pt",
        "类别": "计算机"
    },
    {
        "外文": "Procurar por string",
        "中文": "字符串查找",
        "语种": "pt",
        "类别": "计算机"
    },
    {
        "外文": "Instalação em um clique",
        "中文": "一键安装",
        "语种": "pt",
        "类别": "计算机"
    },
    {
        "外文": "Otimização para SQL",
        "中文": "SQL优化",
        "语种": "pt",
        "类别": "计算机"
    },
    {
        "外文": "Nuvem pública disponível",
        "中文": "公有云",
        "语种": "pt",
        "类别": "计算机"
    },
    {
        "外文": "Estrutura de cache",
        "中文": "缓存框架",
        "语种": "pt",
        "类别": "计算机"
    },
    {
        "外文": "Função de c",
        "中文": "c函数",
        "语种": "pt",
        "类别": "计算机"
    },
    {
        "外文": "Bloco de controle",
        "中文": "控制块",
        "语种": "pt",
        "类别": "计算机"
    },
    {
        "外文": "O daemon",
        "中文": "守护程序",
        "语种": "pt",
        "类别": "计算机"
    },
    {
        "外文": "Configuração do catálogo",
        "中文": "目录配置",
        "语种": "pt",
        "类别": "计算机"
    },
    {
        "外文": "Função com gancho",
        "中文": "钩子函数",
        "语种": "pt",
        "类别": "计算机"
    },
    {
        "外文": "cruz",
        "中文": "叉乘",
        "语种": "pt",
        "类别": "计算机"
    },
    {
        "外文": "Compressão de imagem",
        "中文": "图像压缩",
        "语种": "pt",
        "类别": "计算机"
    },
    {
        "外文": "O código algorítmico",
        "中文": "算法代码",
        "语种": "pt",
        "类别": "计算机"
    },
    {
        "外文": "Tela de inicialização",
        "中文": "启动画面",
        "语种": "pt",
        "类别": "计算机"
    },
    {
        "外文": "Fluxo de despesas",
        "中文": "费用流",
        "语种": "pt",
        "类别": "计算机"
    },
    {
        "外文": "Membros do público",
        "中文": "公有成员",
        "语种": "pt",
        "类别": "计算机"
    },
    {
        "外文": "Publicar uma assinatura",
        "中文": "发布订阅",
        "语种": "pt",
        "类别": "计算机"
    },
    {
        "外文": "Duração do teste",
        "中文": "测试时间",
        "语种": "pt",
        "类别": "计算机"
    },
    {
        "外文": "Modo de saída",
        "中文": "输出模式",
        "语种": "pt",
        "类别": "计算机"
    },
    {
        "外文": "Peça de código",
        "中文": "代码片",
        "语种": "pt",
        "类别": "计算机"
    },
    {
        "外文": "Vigilância por vídeo",
        "中文": "视频监控",
        "语种": "pt",
        "类别": "计算机"
    },
    {
        "外文": "Eliminação gaussiana",
        "中文": "高斯消元",
        "语种": "pt",
        "类别": "计算机"
    },
    {
        "外文": "Parâmetros da matriz",
        "中文": "数组参数",
        "语种": "pt",
        "类别": "计算机"
    },
    {
        "外文": "Adicionar um campo",
        "中文": "增加字段",
        "语种": "pt",
        "类别": "计算机"
    },
    {
        "外文": "Manipulação de caracteres",
        "中文": "字符操作",
        "语种": "pt",
        "类别": "计算机"
    },
    {
        "外文": "Localização por GPS",
        "中文": "GPS定位",
        "语种": "pt",
        "类别": "计算机"
    },
    {
        "外文": "Mapa do vector",
        "中文": "矢量图",
        "语种": "pt",
        "类别": "计算机"
    },
    {
        "外文": "Dados no espaço",
        "中文": "空间数据",
        "语种": "pt",
        "类别": "计算机"
    },
    {
        "外文": "Módulos de terceiros",
        "中文": "第三方模块",
        "语种": "pt",
        "类别": "计算机"
    },
    {
        "外文": "Uso para Linux",
        "中文": "Linux使用",
        "语种": "pt",
        "类别": "计算机"
    },
    {
        "外文": "Processando o fluxo",
        "中文": "处理流",
        "语种": "pt",
        "类别": "计算机"
    },
    {
        "外文": "Abstração de dados",
        "中文": "数据抽象",
        "语种": "pt",
        "类别": "计算机"
    },
    {
        "外文": "Janela de prompt",
        "中文": "提示窗口",
        "语种": "pt",
        "类别": "计算机"
    },
    {
        "外文": "Aplicações de software",
        "中文": "软件应用",
        "语种": "pt",
        "类别": "计算机"
    },
    {
        "外文": "Código para Android",
        "中文": "Android代码",
        "语种": "pt",
        "类别": "计算机"
    },
    {
        "外文": "Criptografia com RSA",
        "中文": "RSA加密",
        "语种": "pt",
        "类别": "计算机"
    },
    {
        "外文": "Discussão por categoria",
        "中文": "分类讨论",
        "语种": "pt",
        "类别": "计算机"
    },
    {
        "外文": "Tipo de acesso",
        "中文": "访问类型",
        "语种": "pt",
        "类别": "计算机"
    },
    {
        "外文": "O comando CMD",
        "中文": "CMD命令",
        "语种": "pt",
        "类别": "计算机"
    },
    {
        "外文": "Referência por const",
        "中文": "const引用",
        "语种": "pt",
        "类别": "计算机"
    },
    {
        "外文": "Ponteiros duplos",
        "中文": "双指针",
        "语种": "pt",
        "类别": "计算机"
    },
    {
        "外文": "Fixa a largura",
        "中文": "固定宽度",
        "语种": "pt",
        "类别": "计算机"
    },
    {
        "外文": "Nenhuma atualização disponível",
        "中文": "无刷新",
        "语种": "pt",
        "类别": "计算机"
    },
    {
        "外文": "Desenvolvimento de empresas",
        "中文": "企业开发",
        "语种": "pt",
        "类别": "计算机"
    },
    {
        "外文": "Interface com GUI",
        "中文": "GUI界面",
        "语种": "pt",
        "类别": "计算机"
    },
    {
        "外文": "Menu de navegação",
        "中文": "导航菜单",
        "语种": "pt",
        "类别": "计算机"
    },
    {
        "外文": "Otimização do sistema",
        "中文": "系统优化",
        "语种": "pt",
        "类别": "计算机"
    },
    {
        "外文": "Uma comunicação móvel",
        "中文": "移动通信",
        "语种": "pt",
        "类别": "计算机"
    },
    {
        "外文": "Formato do tempo",
        "中文": "时间格式",
        "语种": "pt",
        "类别": "计算机"
    },
    {
        "外文": "Execute o stream",
        "中文": "执行流",
        "语种": "pt",
        "类别": "计算机"
    },
    {
        "外文": "Categoria de tecnologia",
        "中文": "技术类",
        "语种": "pt",
        "类别": "计算机"
    },
    {
        "外文": "Tipo de parametrização",
        "中文": "参数化类型",
        "语种": "pt",
        "类别": "计算机"
    },
    {
        "外文": "Aulas vazia.",
        "中文": "空类",
        "语种": "pt",
        "类别": "计算机"
    },
    {
        "外文": "Canal de dados",
        "中文": "数据通道",
        "语种": "pt",
        "类别": "计算机"
    },
    {
        "外文": "Lembrar a senha",
        "中文": "记住密码",
        "语种": "pt",
        "类别": "计算机"
    },
    {
        "外文": "Cópia de string",
        "中文": "字符串拷贝",
        "语种": "pt",
        "类别": "计算机"
    },
    {
        "外文": "Índices não agregados",
        "中文": "非聚集索引",
        "语种": "pt",
        "类别": "计算机"
    },
    {
        "外文": "Mecanismo de processamento de eventos",
        "中文": "事件处理机制",
        "语种": "pt",
        "类别": "计算机"
    },
    {
        "外文": "Pressão de medição",
        "中文": "压测",
        "语种": "pt",
        "类别": "计算机"
    },
    {
        "外文": "O modelo estatístico",
        "中文": "统计模型",
        "语种": "pt",
        "类别": "计算机"
    },
    {
        "外文": "O algoritmo EM",
        "中文": "EM算法",
        "语种": "pt",
        "类别": "计算机"
    },
    {
        "外文": "Uma declaração composta",
        "中文": "复合语句",
        "语种": "pt",
        "类别": "计算机"
    },
    {
        "外文": "Os dados mestres",
        "中文": "主数据",
        "语种": "pt",
        "类别": "计算机"
    },
    {
        "外文": "O protocolo ARP",
        "中文": "ARP协议",
        "语种": "pt",
        "类别": "计算机"
    },
    {
        "外文": "Máquina de alvo",
        "中文": "目标机",
        "语种": "pt",
        "类别": "计算机"
    },
    {
        "外文": "Ferramentas para logging",
        "中文": "日志工具",
        "语种": "pt",
        "类别": "计算机"
    },
    {
        "外文": "Análise de regressão",
        "中文": "回归分析",
        "语种": "pt",
        "类别": "计算机"
    },
    {
        "外文": "O vertex shader",
        "中文": "顶点着色器",
        "语种": "pt",
        "类别": "计算机"
    },
    {
        "外文": "Na rede",
        "中文": "连网",
        "语种": "pt",
        "类别": "计算机"
    },
    {
        "外文": "Classe de algoritmos",
        "中文": "算法类",
        "语种": "pt",
        "类别": "计算机"
    },
    {
        "外文": "Um domínio estático",
        "中文": "静态域",
        "语种": "pt",
        "类别": "计算机"
    },
    {
        "外文": "Triângulo yang hui",
        "中文": "杨辉三角",
        "语种": "pt",
        "类别": "计算机"
    },
    {
        "外文": "Sistema de equações lineares",
        "中文": "线性方程组",
        "语种": "pt",
        "类别": "计算机"
    },
    {
        "外文": "Antepassados públicos recentes",
        "中文": "最近公共祖先",
        "语种": "pt",
        "类别": "计算机"
    },
    {
        "外文": "Substituição de texto",
        "中文": "文本替换",
        "语种": "pt",
        "类别": "计算机"
    },
    {
        "外文": "Grau de semelhança",
        "中文": "相似度",
        "语种": "pt",
        "类别": "计算机"
    },
    {
        "外文": "Ocupação do porto",
        "中文": "端口占用",
        "语种": "pt",
        "类别": "计算机"
    },
    {
        "外文": "Modelos de previsão",
        "中文": "预测模型",
        "语种": "pt",
        "类别": "计算机"
    },
    {
        "外文": "Múltiplas janelas múltiplas",
        "中文": "多窗口",
        "语种": "pt",
        "类别": "计算机"
    },
    {
        "外文": "Estrutura do ramo",
        "中文": "分支结构",
        "语种": "pt",
        "类别": "计算机"
    },
    {
        "外文": "Desenvolvedor de jogos",
        "中文": "游戏开发者",
        "语种": "pt",
        "类别": "计算机"
    },
    {
        "外文": "Geração de números aleatórios",
        "中文": "随机数生成",
        "语种": "pt",
        "类别": "计算机"
    },
    {
        "外文": "Teste de interface",
        "中文": "接口测试",
        "语种": "pt",
        "类别": "计算机"
    },
    {
        "外文": "Carregar a animação",
        "中文": "加载动画",
        "语种": "pt",
        "类别": "计算机"
    },
    {
        "外文": "Pacote e lançamento",
        "中文": "打包发布",
        "语种": "pt",
        "类别": "计算机"
    },
    {
        "外文": "Pacote batimento cardíaco",
        "中文": "心跳包",
        "语种": "pt",
        "类别": "计算机"
    },
    {
        "外文": "A beleza da programação",
        "中文": "编程之美",
        "语种": "pt",
        "类别": "计算机"
    },
    {
        "外文": "Animação com zoom",
        "中文": "缩放动画",
        "语种": "pt",
        "类别": "计算机"
    },
    {
        "外文": "Algoritmos comuns usados",
        "中文": "常用算法",
        "语种": "pt",
        "类别": "计算机"
    },
    {
        "外文": "Consulta por intervalo",
        "中文": "区间查询",
        "语种": "pt",
        "类别": "计算机"
    },
    {
        "外文": "Agitar um pouco",
        "中文": "摇一摇",
        "语种": "pt",
        "类别": "计算机"
    },
    {
        "外文": "Variedade de informações",
        "中文": "各种资料",
        "语种": "pt",
        "类别": "计算机"
    },
    {
        "外文": "Níveis de abstração",
        "中文": "抽象层次",
        "语种": "pt",
        "类别": "计算机"
    },
    {
        "外文": "Pesquisa global por",
        "中文": "全局搜索",
        "语种": "pt",
        "类别": "计算机"
    },
    {
        "外文": "-glacial",
        "中文": "回弹",
        "语种": "pt",
        "类别": "计算机"
    },
    {
        "外文": "O pássaro irmão",
        "中文": "鸟哥",
        "语种": "pt",
        "类别": "计算机"
    },
    {
        "外文": "Não é possível entrar",
        "中文": "无法登录",
        "语种": "pt",
        "类别": "计算机"
    },
    {
        "外文": "Estado da sessão",
        "中文": "会话状态",
        "语种": "pt",
        "类别": "计算机"
    },
    {
        "外文": "Escala de direção de interrupção",
        "中文": "中断向量表",
        "语种": "pt",
        "类别": "计算机"
    },
    {
        "外文": "Programação do núcleo",
        "中文": "核心编程",
        "语种": "pt",
        "类别": "计算机"
    },
    {
        "外文": "Compilar as instruções",
        "中文": "编译指令",
        "语种": "pt",
        "类别": "计算机"
    },
    {
        "外文": "Link de dados",
        "中文": "数据链路",
        "语种": "pt",
        "类别": "计算机"
    },
    {
        "外文": "Configuração do firewall",
        "中文": "防火墙配置",
        "语种": "pt",
        "类别": "计算机"
    },
    {
        "外文": "Mostrar não é completo",
        "中文": "显示不全",
        "语种": "pt",
        "类别": "计算机"
    },
    {
        "外文": "Um computador pessoal",
        "中文": "个人计算机",
        "语种": "pt",
        "类别": "计算机"
    },
    {
        "外文": "Atualização de banco de dados",
        "中文": "数据库更新",
        "语种": "pt",
        "类别": "计算机"
    },
    {
        "外文": "O classificador linear",
        "中文": "线性分类器",
        "语种": "pt",
        "类别": "计算机"
    },
    {
        "外文": "Teorema do resto chinês",
        "中文": "中国剩余定理",
        "语种": "pt",
        "类别": "计算机"
    },
    {
        "外文": "Unidade de estado sólido",
        "中文": "固态硬盘",
        "语种": "pt",
        "类别": "计算机"
    },
    {
        "外文": "Envio de SMS",
        "中文": "短信发送",
        "语种": "pt",
        "类别": "计算机"
    },
    {
        "外文": "Wechat momentos de amigos",
        "中文": "微信朋友圈",
        "语种": "pt",
        "类别": "计算机"
    },
    {
        "外文": "Redes neurais profundas",
        "中文": "深度神经网络",
        "语种": "pt",
        "类别": "计算机"
    },
    {
        "外文": "Classe dentro dos membros",
        "中文": "成员内部类",
        "语种": "pt",
        "类别": "计算机"
    },
    {
        "外文": "Analise o HTML",
        "中文": "解析html",
        "语种": "pt",
        "类别": "计算机"
    },
    {
        "外文": "Relações de classe",
        "中文": "类关系",
        "语种": "pt",
        "类别": "计算机"
    },
    {
        "外文": "A estrutura SSH",
        "中文": "SSH框架",
        "语种": "pt",
        "类别": "计算机"
    },
    {
        "外文": "Função de ponteiro",
        "中文": "指针函数",
        "语种": "pt",
        "类别": "计算机"
    },
    {
        "外文": "Análise de textos",
        "中文": "文本分析",
        "语种": "pt",
        "类别": "计算机"
    },
    {
        "外文": "Remoção de nó",
        "中文": "节点删除",
        "语种": "pt",
        "类别": "计算机"
    },
    {
        "外文": "Para o usuário",
        "中文": "面向用户",
        "语种": "pt",
        "类别": "计算机"
    },
    {
        "外文": "Ponto de interrupção condicional",
        "中文": "条件断点",
        "语种": "pt",
        "类别": "计算机"
    },
    {
        "外文": "Categoria de amigos",
        "中文": "友元类",
        "语种": "pt",
        "类别": "计算机"
    },
    {
        "外文": "O aplicativo nativo",
        "中文": "原生应用",
        "语种": "pt",
        "类别": "计算机"
    },
    {
        "外文": "Armazenamento de dados",
        "中文": "数据储存",
        "语种": "pt",
        "类别": "计算机"
    },
    {
        "外文": "Extensão para PHP",
        "中文": "PHP扩展",
        "语种": "pt",
        "类别": "计算机"
    },
    {
        "外文": "Sistema de arquivos proc",
        "中文": "proc文件系统",
        "语种": "pt",
        "类别": "计算机"
    },
    {
        "外文": "Mapa de atividades",
        "中文": "活动图",
        "语种": "pt",
        "类别": "计算机"
    },
    {
        "外文": "Gestão de equipas",
        "中文": "团队管理",
        "语种": "pt",
        "类别": "计算机"
    },
    {
        "外文": "Cortar um pouco",
        "中文": "割点",
        "语种": "pt",
        "类别": "计算机"
    },
    {
        "外文": "Os livros técnicos",
        "中文": "技术书籍",
        "语种": "pt",
        "类别": "计算机"
    },
    {
        "外文": "Sincronização em tempo real",
        "中文": "实时同步",
        "语种": "pt",
        "类别": "计算机"
    },
    {
        "外文": "Caminho mais curto de fonte única",
        "中文": "单源最短路径",
        "语种": "pt",
        "类别": "计算机"
    },
    {
        "外文": "Árvore do presidente",
        "中文": "主席树",
        "语种": "pt",
        "类别": "计算机"
    },
    {
        "外文": "Ambiente de desenvolvimento Android",
        "中文": "Android开发环境",
        "语种": "pt",
        "类别": "计算机"
    },
    {
        "外文": "O navegador padrão",
        "中文": "默认浏览器",
        "语种": "pt",
        "类别": "计算机"
    },
    {
        "外文": "Uso do controle",
        "中文": "控件使用",
        "语种": "pt",
        "类别": "计算机"
    },
    {
        "外文": "Duplo clique em eventos",
        "中文": "双击事件",
        "语种": "pt",
        "类别": "计算机"
    },
    {
        "外文": "Instalação com Tomcat",
        "中文": "Tomcat安装",
        "语种": "pt",
        "类别": "计算机"
    },
    {
        "外文": "Ver o controle",
        "中文": "视图控件",
        "语种": "pt",
        "类别": "计算机"
    },
    {
        "外文": "Graduate school",
        "中文": "读研",
        "语种": "pt",
        "类别": "计算机"
    },
    {
        "外文": "Concurso de programação",
        "中文": "程序设计竞赛",
        "语种": "pt",
        "类别": "计算机"
    },
    {
        "外文": "Chroma key",
        "中文": "蓝屏",
        "语种": "pt",
        "类别": "计算机"
    },
    {
        "外文": "Desenvolvimento de funcionalidades",
        "中文": "功能开发",
        "语种": "pt",
        "类别": "计算机"
    },
    {
        "外文": "Servidor de imagens",
        "中文": "图片服务器",
        "语种": "pt",
        "类别": "计算机"
    },
    {
        "外文": "Depuração do código",
        "中文": "代码调试",
        "语种": "pt",
        "类别": "计算机"
    },
    {
        "外文": "Ataques de negação de serviço",
        "中文": "拒绝服务攻击",
        "语种": "pt",
        "类别": "计算机"
    },
    {
        "外文": "Inicialização do bloco",
        "中文": "初始化块",
        "语种": "pt",
        "类别": "计算机"
    },
    {
        "外文": "Divisão de fase agitada",
        "中文": "辗转相除法",
        "语种": "pt",
        "类别": "计算机"
    },
    {
        "外文": "Conta pública wechat",
        "中文": "微信公众账号",
        "语种": "pt",
        "类别": "计算机"
    },
    {
        "外文": "Tecnologia orientada a objetos",
        "中文": "面向对象技术",
        "语种": "pt",
        "类别": "计算机"
    },
    {
        "外文": "Conecte e jogue",
        "中文": "即插即用",
        "语种": "pt",
        "类别": "计算机"
    },
    {
        "外文": "A especificação técnica",
        "中文": "技术规范",
        "语种": "pt",
        "类别": "计算机"
    },
    {
        "外文": "Hábitos de codificação",
        "中文": "编码习惯",
        "语种": "pt",
        "类别": "计算机"
    },
    {
        "外文": "Documentação da configuração",
        "中文": "配置文档",
        "语种": "pt",
        "类别": "计算机"
    },
    {
        "外文": "Programação de computadores",
        "中文": "计算机编程",
        "语种": "pt",
        "类别": "计算机"
    },
    {
        "外文": "O intermediário",
        "中文": "中介者",
        "语种": "pt",
        "类别": "计算机"
    },
    {
        "外文": "Desenvolvimento em paralelo",
        "中文": "并行开发",
        "语种": "pt",
        "类别": "计算机"
    },
    {
        "外文": "Serviços de internet",
        "中文": "互联网服务",
        "语种": "pt",
        "类别": "计算机"
    },
    {
        "外文": "Lista de amigos",
        "中文": "好友列表",
        "语种": "pt",
        "类别": "计算机"
    },
    {
        "外文": "Interface de consulta",
        "中文": "查询接口",
        "语种": "pt",
        "类别": "计算机"
    },
    {
        "外文": "Sexo em combinação",
        "中文": "结合性",
        "语种": "pt",
        "类别": "计算机"
    },
    {
        "外文": "Transmissão de documentos",
        "中文": "文件传送",
        "语种": "pt",
        "类别": "计算机"
    },
    {
        "外文": "Recuperação do sistema",
        "中文": "系统恢复",
        "语种": "pt",
        "类别": "计算机"
    },
    {
        "外文": "Atribuição de permissões",
        "中文": "分配权限",
        "语种": "pt",
        "类别": "计算机"
    },
    {
        "外文": "Privacidade do usuário",
        "中文": "用户隐私",
        "语种": "pt",
        "类别": "计算机"
    },
    {
        "外文": "Estrutura de software",
        "中文": "软件框架",
        "语种": "pt",
        "类别": "计算机"
    },
    {
        "外文": "Gestão de aplicações",
        "中文": "应用管理",
        "语种": "pt",
        "类别": "计算机"
    },
    {
        "外文": "Uma pesquisa dicotômica",
        "中文": "二分查找法",
        "语种": "pt",
        "类别": "计算机"
    },
    {
        "外文": "Projetado por API",
        "中文": "API设计",
        "语种": "pt",
        "类别": "计算机"
    },
    {
        "外文": "Acessibilidade e acessibilidade",
        "中文": "可达性",
        "语种": "pt",
        "类别": "计算机"
    },
    {
        "外文": "Contagem automática de referências",
        "中文": "自动引用计数",
        "语种": "pt",
        "类别": "计算机"
    },
    {
        "外文": "Engenheiro de testes",
        "中文": "测试工程师",
        "语种": "pt",
        "类别": "计算机"
    },
    {
        "外文": "Computação de alto desempenho",
        "中文": "高性能计算",
        "语种": "pt",
        "类别": "计算机"
    },
    {
        "外文": "Taxa de recall",
        "中文": "召回率",
        "语种": "pt",
        "类别": "计算机"
    },
    {
        "外文": "Bitcoin por moeda",
        "中文": "比特币",
        "语种": "pt",
        "类别": "计算机"
    },
    {
        "外文": "Planejamento da missão",
        "中文": "任务计划",
        "语种": "pt",
        "类别": "计算机"
    },
    {
        "外文": "O desenvolvimento local",
        "中文": "本地开发",
        "语种": "pt",
        "类别": "计算机"
    },
    {
        "外文": "Travessia de uma árvore binária",
        "中文": "二叉树的遍历",
        "语种": "pt",
        "类别": "计算机"
    },
    {
        "外文": "A instrução include",
        "中文": "include指令",
        "语种": "pt",
        "类别": "计算机"
    },
    {
        "外文": "Travessia de sequência",
        "中文": "层序遍历",
        "语种": "pt",
        "类别": "计算机"
    },
    {
        "外文": "Recuperação de banco de dados",
        "中文": "数据库恢复",
        "语种": "pt",
        "类别": "计算机"
    },
    {
        "外文": "Personalize seu menu",
        "中文": "自定义菜单",
        "语种": "pt",
        "类别": "计算机"
    },
    {
        "外文": "O framework UI",
        "中文": "UI框架",
        "语种": "pt",
        "类别": "计算机"
    },
    {
        "外文": "Mapa em movimento",
        "中文": "动态图",
        "语种": "pt",
        "类别": "计算机"
    },
    {
        "外文": "Atravessando em profundidade",
        "中文": "深度遍历",
        "语种": "pt",
        "类别": "计算机"
    },
    {
        "外文": "Suspensão do processo",
        "中文": "程序暂停",
        "语种": "pt",
        "类别": "计算机"
    },
    {
        "外文": "Modelos de linguagem",
        "中文": "语言模型",
        "语种": "pt",
        "类别": "计算机"
    },
    {
        "外文": "Comunicação por soquete",
        "中文": "Socket通信",
        "语种": "pt",
        "类别": "计算机"
    },
    {
        "外文": "Identificação de impressões digitais",
        "中文": "指纹识别",
        "语种": "pt",
        "类别": "计算机"
    },
    {
        "外文": "Guia de utilização",
        "中文": "使用指南",
        "语种": "pt",
        "类别": "计算机"
    },
    {
        "外文": "Declaração de controle de fluxo",
        "中文": "流程控制语句",
        "语种": "pt",
        "类别": "计算机"
    },
    {
        "外文": "Desenvolvido por eclipse",
        "中文": "eclipse开发",
        "语种": "pt",
        "类别": "计算机"
    },
    {
        "外文": "Método da inserção da cauda",
        "中文": "尾插法",
        "语种": "pt",
        "类别": "计算机"
    },
    {
        "外文": "Par torcido",
        "中文": "双绞线",
        "语种": "pt",
        "类别": "计算机"
    },
    {
        "外文": "Compressão e armazenamento",
        "中文": "压缩存储",
        "语种": "pt",
        "类别": "计算机"
    },
    {
        "外文": "Leia o programa",
        "中文": "阅读程序",
        "语种": "pt",
        "类别": "计算机"
    },
    {
        "外文": "Um depurador",
        "中文": "除错",
        "语种": "pt",
        "类别": "计算机"
    },
    {
        "外文": "Alteração de senha",
        "中文": "密码修改",
        "语种": "pt",
        "类别": "计算机"
    },
    {
        "外文": "Comprimento da chave",
        "中文": "密钥长度",
        "语种": "pt",
        "类别": "计算机"
    },
    {
        "外文": "Descida de gradiente aleatório",
        "中文": "随机梯度下降",
        "语种": "pt",
        "类别": "计算机"
    },
    {
        "外文": "Configuração da primavera",
        "中文": "spring配置",
        "语种": "pt",
        "类别": "计算机"
    },
    {
        "外文": "Deslize para excluir",
        "中文": "滑动删除",
        "语种": "pt",
        "类别": "计算机"
    },
    {
        "外文": "Programa de monitoramento",
        "中文": "监控程序",
        "语种": "pt",
        "类别": "计算机"
    },
    {
        "外文": "Fluxo de saída padrão",
        "中文": "标准输出流",
        "语种": "pt",
        "类别": "计算机"
    },
    {
        "外文": "Política de homólogos",
        "中文": "同源策略",
        "语种": "pt",
        "类别": "计算机"
    },
    {
        "外文": "Estatísticas de probabilidade",
        "中文": "概率统计",
        "语种": "pt",
        "类别": "计算机"
    },
    {
        "外文": "Unidade de medida",
        "中文": "计量单位",
        "语种": "pt",
        "类别": "计算机"
    },
    {
        "外文": "Operações com coleções",
        "中文": "集合运算",
        "语种": "pt",
        "类别": "计算机"
    },
    {
        "外文": "Versão verde disponível",
        "中文": "绿色版",
        "语种": "pt",
        "类别": "计算机"
    },
    {
        "外文": "Atualize seu índice",
        "中文": "更新索引",
        "语种": "pt",
        "类别": "计算机"
    },
    {
        "外文": "Organização e estrutura",
        "中文": "组织架构",
        "语种": "pt",
        "类别": "计算机"
    },
    {
        "外文": "Website desenhado por",
        "中文": "网站设计",
        "语种": "pt",
        "类别": "计算机"
    },
    {
        "外文": "Variedade de classificação",
        "中文": "各种排序",
        "语种": "pt",
        "类别": "计算机"
    },
    {
        "外文": "ruído",
        "中文": "去噪",
        "语种": "pt",
        "类别": "计算机"
    },
    {
        "外文": "Lançamento do programa",
        "中文": "程序发布",
        "语种": "pt",
        "类别": "计算机"
    },
    {
        "外文": "Componentes de código aberto",
        "中文": "开源组件",
        "语种": "pt",
        "类别": "计算机"
    },
    {
        "外文": "Extremidade do tamanho",
        "中文": "大小端",
        "语种": "pt",
        "类别": "计算机"
    },
    {
        "外文": "Imagem para ampliar",
        "中文": "图片放大",
        "语种": "pt",
        "类别": "计算机"
    },
    {
        "外文": "O primeiro paradigma",
        "中文": "第一范式",
        "语种": "pt",
        "类别": "计算机"
    },
    {
        "外文": "Interromper o contexto",
        "中文": "中断上下文",
        "语种": "pt",
        "类别": "计算机"
    },
    {
        "外文": "Controle do sistema",
        "中文": "系统控制",
        "语种": "pt",
        "类别": "计算机"
    },
    {
        "外文": "O sistema core",
        "中文": "核心系统",
        "语种": "pt",
        "类别": "计算机"
    },
    {
        "外文": "Correspondência de dicotomia",
        "中文": "二分图匹配",
        "语种": "pt",
        "类别": "计算机"
    },
    {
        "外文": "Jogar em backstage",
        "中文": "后台播放",
        "语种": "pt",
        "类别": "计算机"
    },
    {
        "外文": "Experiência em baidu",
        "中文": "百度经验",
        "语种": "pt",
        "类别": "计算机"
    },
    {
        "外文": "Os caracteres codificados",
        "中文": "编码字符",
        "语种": "pt",
        "类别": "计算机"
    },
    {
        "外文": "Programação de software",
        "中文": "软件编程",
        "语种": "pt",
        "类别": "计算机"
    },
    {
        "外文": "Saída em ordem inversa",
        "中文": "逆序输出",
        "语种": "pt",
        "类别": "计算机"
    },
    {
        "外文": "Análise de agrupamento",
        "中文": "聚类分析",
        "语种": "pt",
        "类别": "计算机"
    },
    {
        "外文": "Personalize suas fontes",
        "中文": "自定义字体",
        "语种": "pt",
        "类别": "计算机"
    },
    {
        "外文": "Set-top box",
        "中文": "机顶盒",
        "语种": "pt",
        "类别": "计算机"
    },
    {
        "外文": "Herança virtual",
        "中文": "虚继承",
        "语种": "pt",
        "类别": "计算机"
    },
    {
        "外文": "Plano do projeto",
        "中文": "项目计划",
        "语种": "pt",
        "类别": "计算机"
    },
    {
        "外文": "Estado da conexão de rede",
        "中文": "网络连接状态",
        "语种": "pt",
        "类别": "计算机"
    },
    {
        "外文": "Desenvolvido em Python",
        "中文": "Python开发",
        "语种": "pt",
        "类别": "计算机"
    },
    {
        "外文": "Atualizações automáticas automáticas",
        "中文": "自动升级",
        "语种": "pt",
        "类别": "计算机"
    },
    {
        "外文": "Um terminal virtual",
        "中文": "虚拟终端",
        "语种": "pt",
        "类别": "计算机"
    },
    {
        "外文": "Programação de bases de dados",
        "中文": "数据库编程",
        "语种": "pt",
        "类别": "计算机"
    },
    {
        "外文": "Sistemas de comunicação",
        "中文": "通信系统",
        "语种": "pt",
        "类别": "计算机"
    },
    {
        "外文": "Conexão de objetos",
        "中文": "对象连接",
        "语种": "pt",
        "类别": "计算机"
    },
    {
        "外文": "O modelo IO",
        "中文": "IO模型",
        "语种": "pt",
        "类别": "计算机"
    },
    {
        "外文": "Índice secundário",
        "中文": "二级索引",
        "语种": "pt",
        "类别": "计算机"
    },
    {
        "外文": "Gerar um modelo",
        "中文": "生成模型",
        "语种": "pt",
        "类别": "计算机"
    },
    {
        "外文": "Cruz vermelha",
        "中文": "红叉",
        "语种": "pt",
        "类别": "计算机"
    },
    {
        "外文": "Um micro serviço",
        "中文": "微服务",
        "语种": "pt",
        "类别": "计算机"
    },
    {
        "外文": "Mecanismo de transmissão",
        "中文": "广播机制",
        "语种": "pt",
        "类别": "计算机"
    },
    {
        "外文": "Uma atualização local",
        "中文": "局部刷新",
        "语种": "pt",
        "类别": "计算机"
    },
    {
        "外文": "Unidade de nível inferior",
        "中文": "底层驱动",
        "语种": "pt",
        "类别": "计算机"
    },
    {
        "外文": "Para ser adicionado",
        "中文": "待补充",
        "语种": "pt",
        "类别": "计算机"
    },
    {
        "外文": "O segundo paradigma",
        "中文": "第二范式",
        "语种": "pt",
        "类别": "计算机"
    },
    {
        "外文": "Cortar uma imagem",
        "中文": "裁剪图片",
        "语种": "pt",
        "类别": "计算机"
    }
]