[
    {
        "外文": "Tempo e rio",
        "中文": "时令河",
        "语种": "pt",
        "类别": "自然地理"
    },
    {
        "外文": "O rio perene",
        "中文": "常年河",
        "语种": "pt",
        "类别": "自然地理"
    },
    {
        "外文": "O rio subterrâneo",
        "中文": "地下河",
        "语种": "pt",
        "类别": "自然地理"
    },
    {
        "外文": "canal",
        "中文": "运河",
        "语种": "pt",
        "类别": "自然地理"
    },
    {
        "外文": "lake",
        "中文": "湖泊",
        "语种": "pt",
        "类别": "自然地理"
    },
    {
        "外文": "Lago de água doce",
        "中文": "淡水湖",
        "语种": "pt",
        "类别": "自然地理"
    },
    {
        "外文": "O lago interno",
        "中文": "内流湖",
        "语种": "pt",
        "类别": "自然地理"
    },
    {
        "外文": "Lago de saída",
        "中文": "外流湖",
        "语种": "pt",
        "类别": "自然地理"
    },
    {
        "外文": "Construindo o lago",
        "中文": "构造湖",
        "语种": "pt",
        "类别": "自然地理"
    },
    {
        "外文": "O lago vulcânico",
        "中文": "火山湖",
        "语种": "pt",
        "类别": "自然地理"
    },
    {
        "外文": "O lago glacial",
        "中文": "冰川湖",
        "语种": "pt",
        "类别": "自然地理"
    },
    {
        "外文": "Barragem do lago",
        "中文": "堰塞湖",
        "语种": "pt",
        "类别": "自然地理"
    },
    {
        "外文": "Rio em lago",
        "中文": "河成湖",
        "语种": "pt",
        "类别": "自然地理"
    },
    {
        "外文": "Mar em lago",
        "中文": "海成湖",
        "语种": "pt",
        "类别": "自然地理"
    },
    {
        "外文": "pântano",
        "中文": "沼泽",
        "语种": "pt",
        "类别": "自然地理"
    },
    {
        "外文": "As zonas húmidas",
        "中文": "湿地",
        "语种": "pt",
        "类别": "自然地理"
    },
    {
        "外文": "reservatório",
        "中文": "水库",
        "语种": "pt",
        "类别": "自然地理"
    },
    {
        "外文": "Um lago artificial",
        "中文": "人工湖",
        "语种": "pt",
        "类别": "自然地理"
    },
    {
        "外文": "Água subterrânea",
        "中文": "地下水",
        "语种": "pt",
        "类别": "自然地理"
    },
    {
        "外文": "mergulho",
        "中文": "潜水",
        "语种": "pt",
        "类别": "自然地理"
    },
    {
        "外文": "Água sob pressão",
        "中文": "承压水",
        "语种": "pt",
        "类别": "自然地理"
    },
    {
        "外文": "Aquífero de água",
        "中文": "含水层",
        "语种": "pt",
        "类别": "自然地理"
    },
    {
        "外文": "Isolamento de água",
        "中文": "隔水层",
        "语种": "pt",
        "类别": "自然地理"
    },
    {
        "外文": "springs",
        "中文": "泉",
        "语种": "pt",
        "类别": "自然地理"
    },
    {
        "外文": "spa",
        "中文": "温泉",
        "语种": "pt",
        "类别": "自然地理"
    },
    {
        "外文": "Cold spring",
        "中文": "冷泉",
        "语种": "pt",
        "类别": "自然地理"
    },
    {
        "外文": "spa",
        "中文": "矿泉",
        "语种": "pt",
        "类别": "自然地理"
    },
    {
        "外文": "Funil de água subterrânea",
        "中文": "地下水漏斗",
        "语种": "pt",
        "类别": "自然地理"
    },
    {
        "外文": "Nível da água",
        "中文": "水位",
        "语种": "pt",
        "类别": "自然地理"
    },
    {
        "外文": "tráfego",
        "中文": "流量",
        "语种": "pt",
        "类别": "自然地理"
    },
    {
        "外文": "Conteúdo de areia",
        "中文": "含沙量",
        "语种": "pt",
        "类别": "自然地理"
    },
    {
        "外文": "Transporte de areia",
        "中文": "输沙量",
        "语种": "pt",
        "类别": "自然地理"
    },
    {
        "外文": "inundação",
        "中文": "汛期",
        "语种": "pt",
        "类别": "自然地理"
    },
    {
        "外文": "Período de água morta",
        "中文": "枯水期",
        "语种": "pt",
        "类别": "自然地理"
    },
    {
        "外文": "LingXun",
        "中文": "凌汛",
        "语种": "pt",
        "类别": "自然地理"
    },
    {
        "外文": "Idade do gelo",
        "中文": "结冰期",
        "语种": "pt",
        "类别": "自然地理"
    },
    {
        "外文": "Período de navegação",
        "中文": "通航期",
        "语种": "pt",
        "类别": "自然地理"
    },
    {
        "外文": "água",
        "中文": "水能",
        "语种": "pt",
        "类别": "自然地理"
    },
    {
        "外文": "Características hidrológicas",
        "中文": "水文特征",
        "语种": "pt",
        "类别": "自然地理"
    },
    {
        "外文": "Características do sistema hídrico",
        "中文": "水系特征",
        "语种": "pt",
        "类别": "自然地理"
    },
    {
        "外文": "Erosão por rastreabilidade",
        "中文": "溯源侵蚀",
        "语种": "pt",
        "类别": "自然地理"
    },
    {
        "外文": "degradante",
        "中文": "下蚀",
        "语种": "pt",
        "类别": "自然地理"
    },
    {
        "外文": "erosão",
        "中文": "侧蚀",
        "语种": "pt",
        "类别": "自然地理"
    },
    {
        "外文": "deposição",
        "中文": "沉积",
        "语种": "pt",
        "类别": "自然地理"
    },
    {
        "外文": "aluviais",
        "中文": "冲积",
        "语种": "pt",
        "类别": "自然地理"
    },
    {
        "外文": "desânimo",
        "中文": "洪积",
        "语种": "pt",
        "类别": "自然地理"
    },
    {
        "外文": "Deposição em estuário",
        "中文": "河口沉积",
        "语种": "pt",
        "类别": "自然地理"
    },
    {
        "外文": "rio",
        "中文": "河床",
        "语种": "pt",
        "类别": "自然地理"
    },
    {
        "外文": "vale",
        "中文": "河谷",
        "语种": "pt",
        "类别": "自然地理"
    },
    {
        "外文": "Planícies de inundação",
        "中文": "河漫滩",
        "语种": "pt",
        "类别": "自然地理"
    },
    {
        "外文": "delta",
        "中文": "三角洲",
        "语种": "pt",
        "类别": "自然地理"
    },
    {
        "外文": "Ventilador aluvial",
        "中文": "冲积扇",
        "语种": "pt",
        "类别": "自然地理"
    },
    {
        "外文": "pântano",
        "中文": "沼泽化",
        "语种": "pt",
        "类别": "自然地理"
    },
    {
        "外文": "salinização",
        "中文": "盐渍化",
        "语种": "pt",
        "类别": "自然地理"
    },
    {
        "外文": "Erosão do solo",
        "中文": "水土流失",
        "语种": "pt",
        "类别": "自然地理"
    },
    {
        "外文": "Poluição da água",
        "中文": "水体污染",
        "语种": "pt",
        "类别": "自然地理"
    },
    {
        "外文": "eutrofização",
        "中文": "富营养化",
        "语种": "pt",
        "类别": "自然地理"
    },
    {
        "外文": "corrente",
        "中文": "洋流",
        "语种": "pt",
        "类别": "自然地理"
    },
    {
        "外文": "Frente fria",
        "中文": "寒流",
        "语种": "pt",
        "类别": "自然地理"
    },
    {
        "外文": "correntes",
        "中文": "暖流",
        "语种": "pt",
        "类别": "自然地理"
    },
    {
        "外文": "Fluxo de densidade",
        "中文": "密度流",
        "语种": "pt",
        "类别": "自然地理"
    },
    {
        "外文": "Vento e corrente",
        "中文": "风海流",
        "语种": "pt",
        "类别": "自然地理"
    },
    {
        "外文": "Fluxo de compensação",
        "中文": "补偿流",
        "语种": "pt",
        "类别": "自然地理"
    },
    {
        "外文": "Correntes de monção",
        "中文": "季风洋流",
        "语种": "pt",
        "类别": "自然地理"
    },
    {
        "外文": "Rafting vento oeste",
        "中文": "西风漂流",
        "语种": "pt",
        "类别": "自然地理"
    },
    {
        "外文": "Contracorrente equatorial",
        "中文": "赤道逆流",
        "语种": "pt",
        "类别": "自然地理"
    },
    {
        "外文": "Black stream",
        "中文": "黑潮",
        "语种": "pt",
        "类别": "自然地理"
    },
    {
        "外文": "rocha",
        "中文": "岩石",
        "语种": "pt",
        "类别": "自然地理"
    },
    {
        "外文": "Rocha magmática",
        "中文": "岩浆岩",
        "语种": "pt",
        "类别": "自然地理"
    },
    {
        "外文": "Rochas sedimentares",
        "中文": "沉积岩",
        "语种": "pt",
        "类别": "自然地理"
    },
    {
        "外文": "granito",
        "中文": "花岗岩",
        "语种": "pt",
        "类别": "自然地理"
    },
    {
        "外文": "Basalto e rocha",
        "中文": "玄武岩",
        "语种": "pt",
        "类别": "自然地理"
    },
    {
        "外文": "calcário",
        "中文": "石灰岩",
        "语种": "pt",
        "类别": "自然地理"
    },
    {
        "外文": "arenito",
        "中文": "砂岩",
        "语种": "pt",
        "类别": "自然地理"
    },
    {
        "外文": "O xisto",
        "中文": "页岩",
        "语种": "pt",
        "类别": "自然地理"
    },
    {
        "外文": "Mármore e calcário",
        "中文": "大理岩",
        "语种": "pt",
        "类别": "自然地理"
    },
    {
        "外文": "ardósia",
        "中文": "板岩",
        "语种": "pt",
        "类别": "自然地理"
    },
    {
        "外文": "Gneis e rocha",
        "中文": "片麻岩",
        "语种": "pt",
        "类别": "自然地理"
    },
    {
        "外文": "Minério de metal",
        "中文": "金属矿",
        "语种": "pt",
        "类别": "自然地理"
    },
    {
        "外文": "Minerais não metálicos",
        "中文": "非金属矿",
        "语种": "pt",
        "类别": "自然地理"
    },
    {
        "外文": "Energia e mineração",
        "中文": "能源矿",
        "语种": "pt",
        "类别": "自然地理"
    },
    {
        "外文": "cobre",
        "中文": "铜矿",
        "语种": "pt",
        "类别": "自然地理"
    },
    {
        "外文": "minérios",
        "中文": "铝矿",
        "语种": "pt",
        "类别": "自然地理"
    },
    {
        "外文": "zinco",
        "中文": "锌矿",
        "语种": "pt",
        "类别": "自然地理"
    },
    {
        "外文": "Mina de ouro",
        "中文": "金矿",
        "语种": "pt",
        "类别": "自然地理"
    },
    {
        "外文": "Minas de prata",
        "中文": "银矿",
        "语种": "pt",
        "类别": "自然地理"
    },
    {
        "外文": "Minas de carvão",
        "中文": "煤矿",
        "语种": "pt",
        "类别": "自然地理"
    },
    {
        "外文": "O petróleo",
        "中文": "石油",
        "语种": "pt",
        "类别": "自然地理"
    },
    {
        "外文": "Gás natural",
        "中文": "天然气",
        "语种": "pt",
        "类别": "自然地理"
    },
    {
        "外文": "Metais de terras raras",
        "中文": "稀土",
        "语种": "pt",
        "类别": "自然地理"
    },
    {
        "外文": "Gás de carvão",
        "中文": "煤层气",
        "语种": "pt",
        "类别": "自然地理"
    },
    {
        "外文": "Gás de xisto",
        "中文": "页岩气",
        "语种": "pt",
        "类别": "自然地理"
    },
    {
        "外文": "O solo",
        "中文": "土壤",
        "语种": "pt",
        "类别": "自然地理"
    },
    {
        "外文": "Matéria orgânica matéria",
        "中文": "有机质",
        "语种": "pt",
        "类别": "自然地理"
    },
    {
        "外文": "húmus",
        "中文": "腐殖质",
        "语种": "pt",
        "类别": "自然地理"
    },
    {
        "外文": "Camada do solo",
        "中文": "土壤层",
        "语种": "pt",
        "类别": "自然地理"
    },
    {
        "外文": "Camada superficial do solo",
        "中文": "表土层",
        "语种": "pt",
        "类别": "自然地理"
    },
    {
        "外文": "Camadas do coração",
        "中文": "心土层",
        "语种": "pt",
        "类别": "自然地理"
    },
    {
        "外文": "Camada inferior do solo",
        "中文": "底土层",
        "语种": "pt",
        "类别": "自然地理"
    },
    {
        "外文": "Textura do solo",
        "中文": "土壤质地",
        "语种": "pt",
        "类别": "自然地理"
    },
    {
        "外文": "areia",
        "中文": "砂土",
        "语种": "pt",
        "类别": "自然地理"
    },
    {
        "外文": "-argilosos",
        "中文": "壤土",
        "语种": "pt",
        "类别": "自然地理"
    },
    {
        "外文": "O clay",
        "中文": "黏土",
        "语种": "pt",
        "类别": "自然地理"
    },
    {
        "外文": "Estrutura do solo",
        "中文": "土壤结构",
        "语种": "pt",
        "类别": "自然地理"
    },
    {
        "外文": "Estrutura da massa",
        "中文": "团粒结构",
        "语种": "pt",
        "类别": "自然地理"
    },
    {
        "外文": "Fertilidade do solo",
        "中文": "土壤肥力",
        "语种": "pt",
        "类别": "自然地理"
    },
    {
        "外文": "Acidez e alcalinidade do solo",
        "中文": "土壤酸碱度",
        "语种": "pt",
        "类别": "自然地理"
    },
    {
        "外文": "Salinização do solo",
        "中文": "土壤盐渍化",
        "语种": "pt",
        "类别": "自然地理"
    },
    {
        "外文": "Arenização do solo",
        "中文": "土壤沙化",
        "语种": "pt",
        "类别": "自然地理"
    },
    {
        "外文": "Erosão do solo",
        "中文": "土壤侵蚀",
        "语种": "pt",
        "类别": "自然地理"
    },
    {
        "外文": "Erosão do solo",
        "中文": "水土流失",
        "语种": "pt",
        "类别": "自然地理"
    },
    {
        "外文": "Poluição do solo",
        "中文": "土壤污染",
        "语种": "pt",
        "类别": "自然地理"
    },
    {
        "外文": "Melhoramento do solo",
        "中文": "土壤改良",
        "语种": "pt",
        "类别": "自然地理"
    },
    {
        "外文": "Terra vermelha",
        "中文": "红壤",
        "语种": "pt",
        "类别": "自然地理"
    },
    {
        "外文": "brown",
        "中文": "棕壤",
        "语种": "pt",
        "类别": "自然地理"
    },
    {
        "外文": "Terra preta",
        "中文": "黑土",
        "语种": "pt",
        "类别": "自然地理"
    },
    {
        "外文": "Terra calcária preta",
        "中文": "黑钙土",
        "语种": "pt",
        "类别": "自然地理"
    },
    {
        "外文": "Castanha e calcário",
        "中文": "栗钙土",
        "语种": "pt",
        "类别": "自然地理"
    },
    {
        "外文": "Terra do deserto",
        "中文": "荒漠土",
        "语种": "pt",
        "类别": "自然地理"
    },
    {
        "外文": "Terra limnética",
        "中文": "冰沼土",
        "语种": "pt",
        "类别": "自然地理"
    },
    {
        "外文": "Terra de arroz",
        "中文": "水稻土",
        "语种": "pt",
        "类别": "自然地理"
    },
    {
        "外文": "A terra roxa",
        "中文": "紫色土",
        "语种": "pt",
        "类别": "自然地理"
    },
    {
        "外文": "Cal e terra",
        "中文": "石灰土",
        "语种": "pt",
        "类别": "自然地理"
    },
    {
        "外文": "Solos salinos e alcalinos",
        "中文": "盐碱土",
        "语种": "pt",
        "类别": "自然地理"
    },
    {
        "外文": "Terra do pântano",
        "中文": "沼泽土",
        "语种": "pt",
        "类别": "自然地理"
    },
    {
        "外文": "Terra dos prados",
        "中文": "草甸土",
        "语种": "pt",
        "类别": "自然地理"
    },
    {
        "外文": "Terra de prados de montanha",
        "中文": "山地草甸土",
        "语种": "pt",
        "类别": "自然地理"
    },
    {
        "外文": "Terra dos prados subalpinos",
        "中文": "亚高山草甸土",
        "语种": "pt",
        "类别": "自然地理"
    },
    {
        "外文": "O papel geológico",
        "中文": "地质作用",
        "语种": "pt",
        "类别": "自然地理"
    },
    {
        "外文": "Ação da força interna",
        "中文": "内力作用",
        "语种": "pt",
        "类别": "自然地理"
    },
    {
        "外文": "Ação da força externa",
        "中文": "外力作用",
        "语种": "pt",
        "类别": "自然地理"
    },
    {
        "外文": "Ação do intemperismo",
        "中文": "风化作用",
        "语种": "pt",
        "类别": "自然地理"
    },
    {
        "外文": "Ação da erosão",
        "中文": "侵蚀作用",
        "语种": "pt",
        "类别": "自然地理"
    },
    {
        "外文": "Papel do transporte",
        "中文": "搬运作用",
        "语种": "pt",
        "类别": "自然地理"
    },
    {
        "外文": "Ação por deposição",
        "中文": "沉积作用",
        "语种": "pt",
        "类别": "自然地理"
    },
    {
        "外文": "Consolidação e formação de rocha",
        "中文": "固结成岩",
        "语种": "pt",
        "类别": "自然地理"
    },
    {
        "外文": "Efeito da deterioração",
        "中文": "变质作用",
        "语种": "pt",
        "类别": "自然地理"
    },
    {
        "外文": "criaturas",
        "中文": "生物",
        "语种": "pt",
        "类别": "自然地理"
    },
    {
        "外文": "As plantas",
        "中文": "植物",
        "语种": "pt",
        "类别": "自然地理"
    },
    {
        "外文": "Os animais",
        "中文": "动物",
        "语种": "pt",
        "类别": "自然地理"
    },
    {
        "外文": "microrganismo",
        "中文": "微生物",
        "语种": "pt",
        "类别": "自然地理"
    },
    {
        "外文": "população",
        "中文": "种群",
        "语种": "pt",
        "类别": "自然地理"
    },
    {
        "外文": "comunidades",
        "中文": "群落",
        "语种": "pt",
        "类别": "自然地理"
    },
    {
        "外文": "O ecossistema",
        "中文": "生态系统",
        "语种": "pt",
        "类别": "自然地理"
    },
    {
        "外文": "produtor",
        "中文": "生产者",
        "语种": "pt",
        "类别": "自然地理"
    },
    {
        "外文": "Consumidor de",
        "中文": "消费者",
        "语种": "pt",
        "类别": "自然地理"
    },
    {
        "外文": "O descomponedor",
        "中文": "分解者",
        "语种": "pt",
        "类别": "自然地理"
    },
    {
        "外文": "Cadeia alimentar",
        "中文": "食物链",
        "语种": "pt",
        "类别": "自然地理"
    },
    {
        "外文": "A rede alimentar",
        "中文": "食物网",
        "语种": "pt",
        "类别": "自然地理"
    },
    {
        "外文": "O equilíbrio ecológico",
        "中文": "生态平衡",
        "语种": "pt",
        "类别": "自然地理"
    },
    {
        "外文": "A diversidade biológica",
        "中文": "生物多样性",
        "语种": "pt",
        "类别": "自然地理"
    },
    {
        "外文": "Uma espécie rara",
        "中文": "珍稀物种",
        "语种": "pt",
        "类别": "自然地理"
    },
    {
        "外文": "Espécies em perigo",
        "中文": "濒危物种",
        "语种": "pt",
        "类别": "自然地理"
    },
    {
        "外文": "Espécies em extinção",
        "中文": "灭绝物种",
        "语种": "pt",
        "类别": "自然地理"
    },
    {
        "外文": "Espécies exóticas",
        "中文": "外来物种",
        "语种": "pt",
        "类别": "自然地理"
    },
    {
        "外文": "A vegetação",
        "中文": "植被",
        "语种": "pt",
        "类别": "自然地理"
    },
    {
        "外文": "A floresta",
        "中文": "森林",
        "语种": "pt",
        "类别": "自然地理"
    },
    {
        "外文": "prairie",
        "中文": "草原",
        "语种": "pt",
        "类别": "自然地理"
    },
    {
        "外文": "O deserto",
        "中文": "荒漠",
        "语种": "pt",
        "类别": "自然地理"
    },
    {
        "外文": "A tundra",
        "中文": "苔原",
        "语种": "pt",
        "类别": "自然地理"
    },
    {
        "外文": "A meadow",
        "中文": "草甸",
        "语种": "pt",
        "类别": "自然地理"
    },
    {
        "外文": "Vegetação aquática",
        "中文": "水生植被",
        "语种": "pt",
        "类别": "自然地理"
    },
    {
        "外文": "Vegetação alpina",
        "中文": "高山植被",
        "语种": "pt",
        "类别": "自然地理"
    },
    {
        "外文": "Vegetação do litoral",
        "中文": "滨海植被",
        "语种": "pt",
        "类别": "自然地理"
    },
    {
        "外文": "Floresta tropical tropical",
        "中文": "热带雨林",
        "语种": "pt",
        "类别": "自然地理"
    },
    {
        "外文": "Florestas subtropicais perenes folhosas",
        "中文": "亚热带常绿阔叶林",
        "语种": "pt",
        "类别": "自然地理"
    },
    {
        "外文": "Florestas temperadas decíduas folhosas",
        "中文": "温带落叶阔叶林",
        "语种": "pt",
        "类别": "自然地理"
    },
    {
        "外文": "Coníferas boreais",
        "中文": "亚寒带针叶林",
        "语种": "pt",
        "类别": "自然地理"
    },
    {
        "外文": "Pastagens temperadas",
        "中文": "温带草原",
        "语种": "pt",
        "类别": "自然地理"
    },
    {
        "外文": "A savana tropical",
        "中文": "热带草原",
        "语种": "pt",
        "类别": "自然地理"
    },
    {
        "外文": "O deserto tropical",
        "中文": "热带荒漠",
        "语种": "pt",
        "类别": "自然地理"
    },
    {
        "外文": "Zona de vegetação",
        "中文": "植被带",
        "语种": "pt",
        "类别": "自然地理"
    },
    {
        "外文": "Espectro de banda vertical",
        "中文": "垂直带谱",
        "语种": "pt",
        "类别": "自然地理"
    },
    {
        "外文": "Espectro de banda horizontal",
        "中文": "水平带谱",
        "语种": "pt",
        "类别": "自然地理"
    },
    {
        "外文": "O nicho ecológico",
        "中文": "生态位",
        "语种": "pt",
        "类别": "自然地理"
    },
    {
        "外文": "habitat",
        "中文": "栖息地",
        "语种": "pt",
        "类别": "自然地理"
    },
    {
        "外文": "habitat",
        "中文": "生境",
        "语种": "pt",
        "类别": "自然地理"
    },
    {
        "外文": "adaptação",
        "中文": "适应",
        "语种": "pt",
        "类别": "自然地理"
    },
    {
        "外文": "evolução",
        "中文": "进化",
        "语种": "pt",
        "类别": "自然地理"
    },
    {
        "外文": "A seleção natural",
        "中文": "自然选择",
        "语种": "pt",
        "类别": "自然地理"
    },
    {
        "外文": "Uma evolução colaborativa",
        "中文": "协同进化",
        "语种": "pt",
        "类别": "自然地理"
    },
    {
        "外文": "A destruição ecológica",
        "中文": "生态破坏",
        "语种": "pt",
        "类别": "自然地理"
    }
]